timeflux_example/__init__.py
timeflux_example/nodes/__init__.py
timeflux_example/nodes/arithmetic.py
timeflux_example/nodes/dynamic.py
timeflux_example/nodes/signal.py
timeflux_example/nodes/sinus.py
timeflux_example-0.2.0.dist-info/LICENSE
timeflux_example-0.2.0.dist-info/METADATA
timeflux_example-0.2.0.dist-info/WHEEL
timeflux_example-0.2.0.dist-info/top_level.txt
timeflux_example-0.2.0.dist-info/RECORD
